<?xml version="1.0" encoding="utf-8" ?>
<Defs>
	<GeneDef>
		<defName>VQEA_Herculean</defName>
		<label>herculean</label>
		<description>Carriers of this gene possess immense superhuman strength, enabling them to strike with devastating force and carry vast loads with ease. Their blows can shatter bones, and they are never staggered by impact.</description>
		<iconPath>UI/Icons/Genes/Powers/Gene_Herculean</iconPath>
		<displayCategory>Archite</displayCategory>
		<marketValueFactor>1.5</marketValueFactor>
		<biostatCpx>3</biostatCpx>
		<biostatArc>1</biostatArc>
		<biostatMet>0</biostatMet>
		<exclusionTags>
			<li>MeleeDamage</li>
		</exclusionTags>
		<statFactors>
			<MeleeDamageFactor>3</MeleeDamageFactor>
			<VEF_MassCarryCapacity>3</VEF_MassCarryCapacity>
			<CarryingCapacity>3</CarryingCapacity>
			<StaggerDurationFactor>0</StaggerDurationFactor>
		</statFactors>
	</GeneDef>
	<GeneDef>
		<defName>VQEA_Prowess</defName>
		<label>prowess</label>
		<description>Carriers of this gene are masterful close-quarters combatants. Their accuracy and reflexes make them nearly impossible to hit in melee, while their strikes land with flawless precision.</description>
		<iconPath>UI/Icons/Genes/Powers/Gene_Prowess</iconPath>
		<displayCategory>Archite</displayCategory>
		<marketValueFactor>1.5</marketValueFactor>
		<biostatCpx>3</biostatCpx>
		<biostatArc>1</biostatArc>
		<biostatMet>0</biostatMet>
		<statFactors>
			<MeleeHitChance>3</MeleeHitChance>
			<MeleeDodgeChance>3</MeleeDodgeChance>
		</statFactors>
	</GeneDef>
	<GeneDef>
		<defName>VQEA_BlurRunner</defName>
		<label>blur runner</label>
		<description>Carriers of this gene move at blinding speed, making them difficult to target with ranged attacks. Their enhanced reflexes and kinetic control allow them to traverse the battlefield in a blur.</description>
		<iconPath>UI/Icons/Genes/Powers/Gene_BlurRunner</iconPath>
		<displayCategory>Archite</displayCategory>
		<marketValueFactor>1.5</marketValueFactor>
		<exclusionTags>
			<li>MeleeDamage</li>
		</exclusionTags>
		<biostatCpx>3</biostatCpx>
		<biostatArc>1</biostatArc>
		<biostatMet>0</biostatMet>
		<statOffsets>
			<MoveSpeed>1</MoveSpeed>
			<VEF_RangedDodgeChance>0.25</VEF_RangedDodgeChance>
		</statOffsets>
		<statFactors>
			<MoveSpeed>1.2</MoveSpeed>
		</statFactors>
	</GeneDef>
	<GeneDef>
		<defName>VQEA_Woundless</defName>
		<label>woundless</label>
		<description>Carriers of this gene rapidly heal from bleeding wounds. Their flesh seals itself moments after injury, preventing blood loss entirely and allowing them to fight through trauma that would kill others.</description>
		<iconPath>UI/Icons/Genes/Powers/Gene_Woundless</iconPath>
		<displayCategory>Archite</displayCategory>
		<marketValueFactor>1.5</marketValueFactor>
		<exclusionTags>
			<li>WoundHealingRate</li>
		</exclusionTags>
		<biostatCpx>4</biostatCpx>
		<biostatArc>1</biostatArc>
		<biostatMet>0</biostatMet>
		<statFactors>
			<InjuryHealingFactor>8</InjuryHealingFactor>
		</statFactors>
		<modExtensions>
			<li Class="VEF.Genes.GeneExtension">
				<hediffToWholeBody>VQEA_Woundless</hediffToWholeBody>
			</li>
		</modExtensions>
	</GeneDef>
	<GeneDef>
		<defName>VQEA_Marksman</defName>
		<label>marksman</label>
		<description>Carriers of this gene exhibit superhuman ranged precision. Their shots are faster, more accurate, and more lethal, giving them a distinct advantage in any firefight.</description>
		<iconPath>UI/Icons/Genes/Powers/Gene_Marksman</iconPath>
		<displayCategory>Archite</displayCategory>
		<marketValueFactor>1.5</marketValueFactor>
		<exclusionTags>
			<li>ShootingAccuracy</li>
		</exclusionTags>
		<biostatCpx>3</biostatCpx>
		<biostatArc>1</biostatArc>
		<biostatMet>0</biostatMet>
		<statOffsets>
			<ShootingAccuracyPawn>100</ShootingAccuracyPawn>
		</statOffsets>
		<statFactors>
			<RangedCooldownFactor>0.75</RangedCooldownFactor>
			<VEF_RangeAttackSpeedFactor>0.75</VEF_RangeAttackSpeedFactor>
		</statFactors>
	</GeneDef>
	<GeneDef>
		<defName>VQEA_PerfectVision</defName>
		<label>perfect vision</label>
		<description>Carriers of this gene see with supernatural clarity at all distances and in total darkness. They are unaffected by low light or long range, and their perception dramatically improves ranged combat effectiveness.</description>
		<iconPath>UI/Icons/Genes/Powers/Gene_PerfectVision</iconPath>
		<displayCategory>Archite</displayCategory>
		<marketValueFactor>1.5</marketValueFactor>
		<ignoreDarkness>true</ignoreDarkness>
		<exclusionTags>
			<li>ShootingAccuracy</li>
		</exclusionTags>
		<biostatCpx>3</biostatCpx>
		<biostatArc>1</biostatArc>
		<biostatMet>0</biostatMet>
		<statFactors>
			<ShootingAccuracyFactor_Long>1.25</ShootingAccuracyFactor_Long>
			<ShootingAccuracyFactor_Medium>1.15</ShootingAccuracyFactor_Medium>
			<VEF_VerbRangeFactor>1.5</VEF_VerbRangeFactor>
		</statFactors>
	</GeneDef>
	<GeneDef>
		<defName>VQEA_PlasteelSkin</defName>
		<label>plasteel skin</label>
		<exclusionTags>
			<li>AG_Armour</li>
			<li>Armour</li>
			<li>Armor</li>
		</exclusionTags>
		<description>Carriers of this gene possess dense, reinforced dermal armor. Their skin resists bullets, absorbs blunt force, and disperses heat, turning their entire body into a living shield.</description>
		<iconPath>UI/Icons/Genes/Powers/Gene_PlasteelSkin</iconPath>
		<displayCategory>Archite</displayCategory>
		<marketValueFactor>1.5</marketValueFactor>
		<customEffectDescriptions>
			<li>+35% blunt natural armour.</li>
			<li>+50% sharp natural armour.</li>
			<li>+160% heat natural armour.</li>
		</customEffectDescriptions>
		<biostatCpx>3</biostatCpx>
		<biostatArc>1</biostatArc>
		<biostatMet>0</biostatMet>
		<modExtensions>
			<li Class="VEF.Genes.GeneExtension">
				<hediffToWholeBody>VQEA_PlasteelSkin</hediffToWholeBody>
			</li>
		</modExtensions>
	</GeneDef>
	<GeneDef ParentName="GeneHandsBase">
		<defName>VQEA_PlasteelClaws</defName>
		<label>plasteel claws</label>
		<description>Carriers of this gene grow synthetic alloy claws capable of slicing through armor and flesh. These natural weapons are always equipped and strike with brutal efficiency.</description>
		<iconPath>UI/Icons/Genes/Powers/Gene_PlasteelClaws</iconPath>
		<biostatCpx>2</biostatCpx>
		<biostatArc>1</biostatArc>
		<biostatMet>0</biostatMet>
		<displayCategory>Archite</displayCategory>
		<marketValueFactor>1.5</marketValueFactor>
		<modExtensions>
			<li Class="VEF.Genes.GeneExtension">
				<hediffsToBodyParts>
					<li>
						<hediff>VQEA_PlasteelClaws</hediff>
						<bodyparts>
							<li>Hand</li>
							<li>Hand</li>
						</bodyparts>
					</li>
				</hediffsToBodyParts>
			</li>
		</modExtensions>
	</GeneDef>
	<GeneDef>
		<defName>VQEA_Genius</defName>
		<label>genius</label>
		<description>Carriers of this gene learn at phenomenal speed and retain all knowledge. They do not suffer skill decay and can interface with technology at unmatched speeds, completing hacking tasks instantly.</description>
		<iconPath>UI/Icons/Genes/Powers/Gene_Genius</iconPath>
		<displayCategory>Archite</displayCategory>
		<marketValueFactor>1.5</marketValueFactor>
		<exclusionTags>
			<li>Learning</li>
		</exclusionTags>
		<biostatCpx>4</biostatCpx>
		<biostatArc>1</biostatArc>
		<biostatMet>0</biostatMet>
		<statOffsets>
			<GlobalLearningFactor>2</GlobalLearningFactor>
			<HackingSpeed>10</HackingSpeed>
		</statOffsets>
		<modExtensions>
			<li Class="VEF.Genes.GeneExtension">
				<globalSkillLossMultiplier>0</globalSkillLossMultiplier>
			</li>
		</modExtensions>
	</GeneDef>
	<GeneDef>
		<defName>VQEA_Levitation</defName>
		<label>levitation</label>
		<iconPath>UI/Icons/Genes/Powers/Gene_Levitation</iconPath>
		<description>Carriers of this gene can lift themselves using a controlled psychic field. They float over obstacles and terrain unharmed, immune to damage during transit and unaffected by difficult terrain.</description>
		<displayCategory>Archite</displayCategory>
		<marketValueFactor>1.5</marketValueFactor>
		<biostatCpx>3</biostatCpx>
		<biostatArc>1</biostatArc>
		<biostatMet>0</biostatMet>
		<abilities>
			<li>VQEA_Levitation</li>
		</abilities>
		<descriptionHyperlinks>
			<AbilityDef>VQEA_Levitation</AbilityDef>
		</descriptionHyperlinks>
	</GeneDef>
	<GeneDef>
		<defName>VQEA_Serene</defName>
		<label>serene</label>
		<description>Carriers of this gene have archites embedded in their neural pathways that suppress fear, anger, and stress responses. As a result, they are utterly unshakable, incapable of mental breaks, social fights, or resisting arrest.</description>
		<iconPath>UI/Icons/Genes/Powers/Gene_Serene</iconPath>
		<displayCategory>Archite</displayCategory>
		<marketValueFactor>1.5</marketValueFactor>
		<exclusionTags>
			<li>Aggression</li>
		</exclusionTags>
		<biostatCpx>4</biostatCpx>
		<biostatArc>1</biostatArc>
		<biostatMet>0</biostatMet>
		<socialFightChanceFactor>0</socialFightChanceFactor>
		<aggroMentalBreakSelectionChanceFactor>0</aggroMentalBreakSelectionChanceFactor>
		<prisonBreakMTBFactor>-1</prisonBreakMTBFactor>
	</GeneDef>
	<GeneDef>
		<defName>VQEA_PassiveMeditation</defName>
		<label>passive meditation</label>
		<description>Carriers of this gene possess archites that passively channel ambient psychic energy, replenishing psyfocus without meditation. These ever-attuned minds remain sharp, composed, and ready to cast at all times.</description>
		<iconPath>UI/Icons/Genes/Powers/Gene_PassiveMeditation</iconPath>
		<displayCategory>Archite</displayCategory>
		<marketValueFactor>1.5</marketValueFactor>
		<biostatCpx>3</biostatCpx>
		<biostatArc>1</biostatArc>
		<biostatMet>0</biostatMet>
		<modExtensions>
			<li Class="VEF.Genes.GeneExtension">
				<hediffToWholeBody>VQEA_PassiveMeditation</hediffToWholeBody>
			</li>
		</modExtensions>
		<customEffectDescriptions>
			<li>Passively regenerates 0.5% psyfocus per hour.</li>
		</customEffectDescriptions>
	</GeneDef>
	<GeneDef>
		<defName>VQEA_Bulwark</defName>
		<label>bulwark</label>
		<description>Archites within the carrier’s tissues reinforce cellular structures, reducing incoming damage by half. Pain receptors are dampened in favor of combat awareness, and the body itself resists trauma that would cripple an ordinary human.</description>
		<iconPath>UI/Icons/Genes/Powers/Gene_Bulwark</iconPath>
		<displayCategory>Archite</displayCategory>
		<marketValueFactor>1.5</marketValueFactor>
		<exclusionTags>
			<li>Toughness</li>
		</exclusionTags>
		<biostatCpx>3</biostatCpx>
		<biostatArc>1</biostatArc>
		<biostatMet>0</biostatMet>
		<statFactors>
			<IncomingDamageFactor>0.5</IncomingDamageFactor>
		</statFactors>
		<modExtensions>
			<li Class="VEF.Genes.GeneExtension">
				<hediffToWholeBody>VQEA_Bulwark</hediffToWholeBody>
			</li>
		</modExtensions>
	</GeneDef>
	<GeneDef>
		<defName>VQEA_Enormous</defName>
		<label>enormous</label>
		<description>Carriers of this gene are saturated with growth-regulating archites that massively increase body size and muscle mass. Their immense frame allows for feats of brute strength, at the cost of speed and appetite.</description>
		<iconPath>UI/Icons/Genes/Powers/Gene_Enormous</iconPath>
		<displayCategory>Archite</displayCategory>
		<marketValueFactor>1.5</marketValueFactor>
		<exclusionTags>
			<li>InsectorSize</li>
		</exclusionTags>
		<biostatCpx>4</biostatCpx>
		<biostatArc>1</biostatArc>
		<biostatMet>0</biostatMet>
		<statOffsets>
			<VEF_BodySize_Offset>1</VEF_BodySize_Offset>
			<MoveSpeed>-1.5</MoveSpeed>
		</statOffsets>
		<statFactors>
			<StaggerDurationFactor>0.2</StaggerDurationFactor>
			<MeatAmount>3</MeatAmount>
			<LeatherAmount>3</LeatherAmount>
			<VEF_FoodCapacityMultiplier>3</VEF_FoodCapacityMultiplier>
			<MeleeDodgeChance>0.25</MeleeDodgeChance>
		</statFactors>
		<modExtensions>
			<li Class="VEF.Genes.GeneExtension">
				<hediffToWholeBody>VQEA_Enormous</hediffToWholeBody>
			</li>
		</modExtensions>
	</GeneDef>
	<GeneDef>
		<defName>VQEA_SubstanceImpervious</defName>
		<label>substance impervious</label>
		<description>Specialized detoxifying archites patrol the bloodstream of carriers, instantly neutralizing addictive compounds and preventing overdose. No drug, however potent, can compromise their system.</description>
		<iconPath>UI/Icons/Genes/Powers/Gene_SubstanceImpervious</iconPath>
		<displayCategory>Archite</displayCategory>
		<marketValueFactor>1.5</marketValueFactor>
		<biostatCpx>3</biostatCpx>
		<biostatArc>1</biostatArc>
		<biostatMet>0</biostatMet>
	</GeneDef>
	<GeneDef>
		<defName>VQEA_MasterfulAnimals</defName>
		<label>masterful animals</label>
		<description>The carrier's aptitude in Animals is increased by 16. Aptitude acts like an offset on skill level. Additionally, two levels of passion are added to Animals. Specialized archites embedded in the limbic system and motor cortex enable this enhanced empathy and coordination, creating a unique form of joy called animal relaxation while tending to animals.</description>
		<iconPath>UI/Icons/Genes/Powers/Gene_AptitudeMasterful_Animals</iconPath>
		<displayCategory>VQEA_ArchiteAptitudes</displayCategory>
		<marketValueFactor>1.5</marketValueFactor>
		<exclusionTags>
			<li>MasterfulSkills</li>
		</exclusionTags>
		<biostatCpx>3</biostatCpx>
		<biostatArc>1</biostatArc>
		<biostatMet>0</biostatMet>
		<aptitudes>
			<Animals>16</Animals>
		</aptitudes>
		<passionMod>
			<skill>Animals</skill>
			<modType>DropAll</modType>
		</passionMod>
	</GeneDef>
	<GeneDef>
		<defName>VQEA_MasterfulArtistic</defName>
		<label>masterful artistic</label>
		<description>The carrier's aptitude in Artistic is increased by 16. Aptitude acts like an offset on skill level. Additionally, two levels of passion are added to Artistic. They work with intense passion, and when they create a masterpiece, a portion of the resources used is miraculously reclaimed. This is made possible by archites that optimize muscle memory and visual-spatial reasoning, recycling material with remarkable efficiency.</description>
		<iconPath>UI/Icons/Genes/Powers/Gene_AptitudeMasterful_Artistic</iconPath>
		<displayCategory>VQEA_ArchiteAptitudes</displayCategory>
		<marketValueFactor>1.5</marketValueFactor>
		<exclusionTags>
			<li>MasterfulSkills</li>
		</exclusionTags>
		<biostatCpx>3</biostatCpx>
		<biostatArc>1</biostatArc>
		<biostatMet>0</biostatMet>
		<aptitudes>
			<Artistic>16</Artistic>
		</aptitudes>
		<passionMod>
			<skill>Artistic</skill>
			<modType>DropAll</modType>
		</passionMod>
	</GeneDef>
	<GeneDef>
		<defName>VQEA_MasterfulConstruction</defName>
		<label>masterful construction</label>
		<description>The carrier's aptitude in Construction is increased by 16. Aptitude acts like an offset on skill level. Additionally, two levels of passion are added to Construction. Occasionally, they exceed expectations, returning some of the materials used during construction as a result of their efficiency.</description>
		<iconPath>UI/Icons/Genes/Powers/Gene_AptitudeMasterful_Construction</iconPath>
		<displayCategory>VQEA_ArchiteAptitudes</displayCategory>
		<marketValueFactor>1.5</marketValueFactor>
		<exclusionTags>
			<li>MasterfulSkills</li>
		</exclusionTags>
		<biostatCpx>3</biostatCpx>
		<biostatArc>1</biostatArc>
		<biostatMet>0</biostatMet>
		<aptitudes>
			<Construction>16</Construction>
		</aptitudes>
		<passionMod>
			<skill>Construction</skill>
			<modType>DropAll</modType>
		</passionMod>
	</GeneDef>
	<GeneDef>
		<defName>VQEA_MasterfulCooking</defName>
		<label>masterful cooking</label>
		<description>The carrier's aptitude in Cooking is increased by 16. Aptitude acts like an offset on skill level. Additionally, two levels of passion are added to Cooking. Nanoscopic archites in the sensory cortex fine-tune taste and motor control, doubling the cooking speed.</description>
		<iconPath>UI/Icons/Genes/Powers/Gene_AptitudeMasterful_Cooking</iconPath>
		<displayCategory>VQEA_ArchiteAptitudes</displayCategory>
		<marketValueFactor>1.5</marketValueFactor>
		<exclusionTags>
			<li>MasterfulSkills</li>
		</exclusionTags>
		<biostatCpx>3</biostatCpx>
		<biostatArc>1</biostatArc>
		<biostatMet>0</biostatMet>
		<aptitudes>
			<Cooking>16</Cooking>
		</aptitudes>
		<statFactors>
			<CookSpeed>2</CookSpeed>
		</statFactors>
		<passionMod>
			<skill>Cooking</skill>
			<modType>DropAll</modType>
		</passionMod>
	</GeneDef>
	<GeneDef>
		<defName>VQEA_MasterfulCrafting</defName>
		<label>masterful crafting</label>
		<description>The carrier's aptitude in Crafting is increased by 16. Aptitude acts like an offset on skill level. Additionally, two levels of passion are added to Crafting. Archites guide the carrier’s fine motor skills and decision-making, ensuring peak performance in crafting.</description>
		<iconPath>UI/Icons/Genes/Powers/Gene_AptitudeMasterful_Crafting</iconPath>
		<displayCategory>VQEA_ArchiteAptitudes</displayCategory>
		<marketValueFactor>1.5</marketValueFactor>
		<exclusionTags>
			<li>MasterfulSkills</li>
		</exclusionTags>
		<biostatCpx>3</biostatCpx>
		<biostatArc>1</biostatArc>
		<biostatMet>0</biostatMet>
		<aptitudes>
			<Crafting>16</Crafting>
		</aptitudes>
		<passionMod>
			<skill>Crafting</skill>
			<modType>DropAll</modType>
		</passionMod>
	</GeneDef>
	<GeneDef>
		<defName>VQEA_MasterfulMedical</defName>
		<label>masterful medical</label>
		<description>The carrier's aptitude in Medical is increased by 16. Aptitude acts like an offset on skill level. Additionally, two levels of passion are added to Medical. Archites enhance decision-making and precision during operations, and provide a 50% chance to preserve medicine during treatment.</description>
		<iconPath>UI/Icons/Genes/Powers/Gene_AptitudeMasterful_Medical</iconPath>
		<displayCategory>VQEA_ArchiteAptitudes</displayCategory>
		<marketValueFactor>1.5</marketValueFactor>
		<exclusionTags>
			<li>MasterfulSkills</li>
		</exclusionTags>
		<biostatCpx>3</biostatCpx>
		<biostatArc>1</biostatArc>
		<biostatMet>0</biostatMet>
		<aptitudes>
			<Medicine>16</Medicine>
		</aptitudes>
		<passionMod>
			<skill>Medicine</skill>
			<modType>DropAll</modType>
		</passionMod>
	</GeneDef>
	<GeneDef>
		<defName>VQEA_MasterfulMelee</defName>
		<label>masterful melee</label>
		<description>The carrier's aptitude in Melee is increased by 16. Aptitude acts like an offset on skill level. Additionally, two levels of passion are added to Melee. They instinctively strike for the heart or brain, dispatching enemies with terrifying efficiency. Archites synchronize muscle memory and visual targeting systems to prioritize lethal organs in combat.</description>
		<iconPath>UI/Icons/Genes/Powers/Gene_AptitudeMasterful_Melee</iconPath>
		<displayCategory>VQEA_ArchiteAptitudes</displayCategory>
		<marketValueFactor>1.5</marketValueFactor>
		<exclusionTags>
			<li>MasterfulSkills</li>
		</exclusionTags>
		<biostatCpx>3</biostatCpx>
		<biostatArc>1</biostatArc>
		<biostatMet>0</biostatMet>
		<aptitudes>
			<Melee>16</Melee>
		</aptitudes>
		<passionMod>
			<skill>Melee</skill>
			<modType>DropAll</modType>
		</passionMod>
	</GeneDef>
	<GeneDef>
		<defName>VQEA_MasterfulMining</defName>
		<label>masterful mining</label>
		<description>The carrier's aptitude in Mining is increased by 16. Aptitude acts like an offset on skill level. Additionally, two levels of passion are added to Mining. Archites augment perception of mineral seams and tool control, granting increased yield and removing any usual mining yield caps.</description>
		<iconPath>UI/Icons/Genes/Powers/Gene_AptitudeMasterful_Mining</iconPath>
		<displayCategory>VQEA_ArchiteAptitudes</displayCategory>
		<marketValueFactor>1.5</marketValueFactor>
		<exclusionTags>
			<li>MasterfulSkills</li>
		</exclusionTags>
		<biostatCpx>3</biostatCpx>
		<biostatArc>1</biostatArc>
		<biostatMet>0</biostatMet>
		<aptitudes>
			<Mining>16</Mining>
		</aptitudes>
		<statOffsets>
			<MiningYield>0.25</MiningYield>
		</statOffsets>
		<passionMod>
			<skill>Mining</skill>
			<modType>DropAll</modType>
		</passionMod>
	</GeneDef>
	<GeneDef>
		<defName>VQEA_MasterfulPlants</defName>
		<label>masterful plants</label>
		<description>The carrier's aptitude in Plants is increased by 16. Aptitude acts like an offset on skill level. Additionally, two levels of passion are added to Plants. Their expertise removes standard yield limits, allowing for extraordinary agricultural output.</description>
		<iconPath>UI/Icons/Genes/Powers/Gene_AptitudeMasterful_Plants</iconPath>
		<displayCategory>VQEA_ArchiteAptitudes</displayCategory>
		<marketValueFactor>1.5</marketValueFactor>
		<exclusionTags>
			<li>MasterfulSkills</li>
		</exclusionTags>
		<biostatCpx>3</biostatCpx>
		<biostatArc>1</biostatArc>
		<biostatMet>0</biostatMet>
		<aptitudes>
			<Plants>16</Plants>
		</aptitudes>
		<statOffsets>
			<PlantHarvestYield>0.3</PlantHarvestYield>
		</statOffsets>
		<passionMod>
			<skill>Plants</skill>
			<modType>DropAll</modType>
		</passionMod>
	</GeneDef>
	<GeneDef>
		<defName>VQEA_MasterfulIntellectual</defName>
		<label>masterful intellectual</label>
		<description>The carrier's aptitude in Intellectual is increased by 16. Aptitude acts like an offset on skill level. Additionally, two levels of passion are added to Intellectual. They conduct research subconsciously, constantly generating scientific progress even while performing other tasks or resting. Archites woven into their neural network accelerate retention, synthesis, and intuition, allowing discoveries to emerge without active study.</description>
		<iconPath>UI/Icons/Genes/Powers/Gene_AptitudeMasterful_Intellectual</iconPath>
		<displayCategory>VQEA_ArchiteAptitudes</displayCategory>
		<marketValueFactor>1.5</marketValueFactor>
		<exclusionTags>
			<li>MasterfulSkills</li>
		</exclusionTags>
		<biostatCpx>3</biostatCpx>
		<biostatArc>1</biostatArc>
		<biostatMet>0</biostatMet>
		<aptitudes>
			<Intellectual>16</Intellectual>
		</aptitudes>
		<passionMod>
			<skill>Intellectual</skill>
			<modType>DropAll</modType>
		</passionMod>
		<modExtensions>
			<li Class="VEF.Genes.GeneExtension">
				<hediffToWholeBody>VQEA_MasterfulIntellectual</hediffToWholeBody>
			</li>
		</modExtensions>
	</GeneDef>
	<GeneDef>
		<defName>VQEA_MasterfulShooting</defName>
		<label>masterful shooting</label>
		<description>The carrier's aptitude in Shooting is increased by 16. Aptitude acts like an offset on skill level. Additionally, two levels of passion are added to Shooting. Every shot is precisely placed: if a head is present, it will be hit. Archites modify visual tracking and ballistic prediction, locking onto cranial targets with terrifying consistency.</description>
		<iconPath>UI/Icons/Genes/Powers/Gene_AptitudeMasterful_Shooting</iconPath>
		<displayCategory>VQEA_ArchiteAptitudes</displayCategory>
		<marketValueFactor>1.5</marketValueFactor>
		<exclusionTags>
			<li>MasterfulSkills</li>
		</exclusionTags>
		<biostatCpx>3</biostatCpx>
		<biostatArc>1</biostatArc>
		<biostatMet>0</biostatMet>
		<aptitudes>
			<Shooting>16</Shooting>
		</aptitudes>
		<passionMod>
			<skill>Shooting</skill>
			<modType>DropAll</modType>
		</passionMod>
	</GeneDef>
	<GeneDef>
		<defName>VQEA_MasterfulSocial</defName>
		<label>masterful social</label>
		<description>The carrier's aptitude in Social is increased by 16. Aptitude acts like an offset on skill level. Additionally, two levels of passion are added to Social. They can recruit even the most unwavering pawns and exert immense ideological influence.</description>
		<iconPath>UI/Icons/Genes/Powers/Gene_AptitudeMasterful_Social</iconPath>
		<displayCategory>VQEA_ArchiteAptitudes</displayCategory>
		<marketValueFactor>1.5</marketValueFactor>
		<exclusionTags>
			<li>MasterfulSkills</li>
		</exclusionTags>
		<biostatCpx>3</biostatCpx>
		<biostatArc>1</biostatArc>
		<biostatMet>0</biostatMet>
		<aptitudes>
			<Social>16</Social>
		</aptitudes>
		<statOffsets>
			<ConversionPower MayRequire="Ludeon.RimWorld.Ideology">1</ConversionPower>
		</statOffsets>
		<passionMod>
			<skill>Social</skill>
			<modType>DropAll</modType>
		</passionMod>
	</GeneDef>
	<GeneDef>
		<defName>VQEA_InfernoSpew</defName>
		<label>inferno spew</label>
		<description>Carriers of this gene can unleash a superheated stream of igniting bile, covering enemies and terrain in burning liquid. This ability turns any battlefield into a fiery trap.</description>
		<iconPath>UI/Icons/Genes/Powers/Gene_InfernoSpew</iconPath>
		<displayCategory>Archite</displayCategory>
		<marketValueFactor>1.5</marketValueFactor>
		<biostatCpx>3</biostatCpx>
		<biostatArc>1</biostatArc>
		<biostatMet>0</biostatMet>
		<abilities>
			<li>VQEA_InfernoSpew</li>
		</abilities>
		<descriptionHyperlinks>
			<AbilityDef>VQEA_InfernoSpew</AbilityDef>
		</descriptionHyperlinks>
	</GeneDef>
	<GeneDef>
		<defName>VQEA_HellsphereBlast</defName>
		<label>hellsphere blast</label>
		<description>Carriers of this gene can emit a devastating beam of energy from their eyes, vaporizing everything in its path. It mimics the firepower of a hellsphere cannon, condensed into a humanoid frame.</description>
		<iconPath>UI/Icons/Genes/Powers/Gene_HellsphereBlast</iconPath>
		<displayCategory>Archite</displayCategory>
		<marketValueFactor>1.5</marketValueFactor>
		<biostatCpx>4</biostatCpx>
		<biostatArc>1</biostatArc>
		<biostatMet>0</biostatMet>
		<abilities>
			<li>VQEA_HellsphereBlast</li>
		</abilities>
		<descriptionHyperlinks>
			<AbilityDef>VQEA_HellsphereBlast</AbilityDef>
		</descriptionHyperlinks>
	</GeneDef>
</Defs>